MANIFEST.in
README.rst
setup.py
redistruct/__init__.py
redistruct/core.py
redistruct/redis.py
redistruct/version.txt
redistruct.egg-info/PKG-INFO
redistruct.egg-info/SOURCES.txt
redistruct.egg-info/dependency_links.txt
redistruct.egg-info/requires.txt
redistruct.egg-info/top_level.txt