Metadata-Version: 1.0
Name: redistruct
Version: 0.0.1
Summary: Human-friendly structured redis API wrapper.
Home-page: https://github.com/youknowone/redistruct
Author: Jeong YunWon
Author-email: redistruct@youknowone.org
License: UNKNOWN
Platform: UNKNOWN
Classifier: Intended Audience :: Developers
Classifier: Operating System :: OS Independent
Classifier: Programming Language :: Python
Classifier: Programming Language :: Python :: 2
Classifier: Programming Language :: Python :: 2.6
Classifier: Programming Language :: Python :: 2.7
